{"devicePlatform":"","logFolder":"C:\\Users\\Asset-192\\Katalon Studio\\Workilo\\Reports\\sign up\\20181115_204024","runData":{"hostName":"Asset-192 - WINCTRL-I1MBNJ3","os":"Windows 8.1 64bit","katalonVersion":"5.8.6.1","browser":"Chrome 70.0.3538.102","hostAddress":"192.168.0.110","sessionId":"7e5408cd7869649e66a67dc3af2b1d2c","seleniumVersion":"3.7.1","proxyInformation":"ProxyInformation{proxyOption\u003dNO_PROXY, proxyServerType\u003dHTTP, password\u003d, proxyServerAddress\u003d, proxyServerPort\u003d0}","platform":"Windows 8.1"},"type":"TEST_SUITE","name":"sign up","id":"Test Suites/sign up","source":"","message":"Test Cases/Sign-Up for Customer with Valid Inputs","description":"","startTime":1542294627974,"endTime":1542294663200,"childRecords":[{"isOptional":false,"type":"TEST_CASE","name":"Test Cases/Sign-Up for Customer with Valid Inputs","id":"Test Cases/Sign-Up for Customer with Valid Inputs","source":"C:\\\\Users\\\\Asset-192\\\\Katalon Studio\\\\Workilo\\\\Test Cases\\\\Sign-Up for Customer with Valid Inputs.tc","message":"Test Cases/Sign-Up for Customer with Valid Inputs","description":"","startTime":1542294628621,"endTime":1542294663143,"childRecords":[{"testStatus":{"stackTrace":"","statusValue":"INFO"},"type":"MESSAGE","name":"","message":"Evaluating variables for test case","startTime":1542294628684,"endTime":0,"childRecords":[],"interuppted":false},{"index":1,"isIgnoredIfFailed":false,"type":"TEST_STEP","name":"Statement - For ([row \u003d 1, row \u003c\u003d com.kms.katalon.core.testdata.TestDataFactory.findTestData(signup_customer).getRowNumbers(), (row++)])","message":"Browser is closed","description":"","startTime":1542294629137,"endTime":1542294663142,"childRecords":[{"index":1,"isIgnoredIfFailed":false,"type":"TEST_STEP","name":"openBrowser","message":"Browser is opened with url: \u0027\u0027","description":"","startTime":1542294629759,"endTime":1542294636507,"childRecords":[{"testStatus":{"stackTrace":"","statusValue":"PASSED"},"type":"MESSAGE","name":"","message":"Browser is opened with url: \u0027\u0027","startTime":1542294636505,"endTime":0,"childRecords":[],"interuppted":false}],"interuppted":false},{"index":2,"isIgnoredIfFailed":false,"type":"TEST_STEP","name":"navigateToUrl","message":"Navigate to \u0027https://www.workilo.com/\u0027 successfully","description":"","startTime":1542294636508,"endTime":1542294657291,"childRecords":[{"testStatus":{"stackTrace":"","statusValue":"PASSED"},"type":"MESSAGE","name":"","message":"Navigate to \u0027https://www.workilo.com/\u0027 successfully","startTime":1542294657289,"endTime":0,"childRecords":[],"interuppted":false}],"interuppted":false},{"index":3,"isIgnoredIfFailed":false,"type":"TEST_STEP","name":"maximizeWindow","message":"Current window maximized","description":"","startTime":1542294657292,"endTime":1542294658481,"childRecords":[{"testStatus":{"stackTrace":"","statusValue":"PASSED"},"type":"MESSAGE","name":"","message":"Current window maximized","startTime":1542294658480,"endTime":0,"childRecords":[],"interuppted":false}],"interuppted":false},{"index":4,"isIgnoredIfFailed":false,"type":"TEST_STEP","name":"clickEvent.SelectServices.clickUsingJS1","message":"clickEvent.SelectServices.clickUsingJS1 is PASSED","description":"","startTime":1542294658482,"endTime":1542294658775,"childRecords":[{"testStatus":{"stackTrace":"","statusValue":"PASSED"},"type":"MESSAGE","name":"","message":"clickEvent.SelectServices.clickUsingJS1 is PASSED","startTime":1542294658774,"endTime":0,"childRecords":[],"interuppted":false}],"interuppted":false},{"index":5,"isIgnoredIfFailed":false,"type":"TEST_STEP","name":"click","message":"Object: \u0027Object Repository/Signup_Customer/customer_menu\u0027 is clicked on","description":"","startTime":1542294658776,"endTime":1542294659126,"childRecords":[{"testStatus":{"stackTrace":"","statusValue":"PASSED"},"type":"MESSAGE","name":"","message":"Object: \u0027Object Repository/Signup_Customer/customer_menu\u0027 is clicked on","startTime":1542294659125,"endTime":0,"childRecords":[],"interuppted":false}],"interuppted":false},{"index":6,"isIgnoredIfFailed":false,"type":"TEST_STEP","name":"setText","message":"Text \u0027naz2@gmail.com\u0027 is set on object \u0027Object Repository/Signup_Customer/email\u0027","description":"","startTime":1542294659126,"endTime":1542294659617,"childRecords":[{"testStatus":{"stackTrace":"","statusValue":"PASSED"},"type":"MESSAGE","name":"","message":"Text \u0027naz2@gmail.com\u0027 is set on object \u0027Object Repository/Signup_Customer/email\u0027","startTime":1542294659616,"endTime":0,"childRecords":[],"interuppted":false}],"interuppted":false},{"index":7,"isIgnoredIfFailed":false,"type":"TEST_STEP","name":"setText","message":"Text \u0027naz\u0027 is set on object \u0027Object Repository/Signup_Customer/first name\u0027","description":"","startTime":1542294659617,"endTime":1542294659898,"childRecords":[{"testStatus":{"stackTrace":"","statusValue":"PASSED"},"type":"MESSAGE","name":"","message":"Text \u0027naz\u0027 is set on object \u0027Object Repository/Signup_Customer/first name\u0027","startTime":1542294659897,"endTime":0,"childRecords":[],"interuppted":false}],"interuppted":false},{"index":8,"isIgnoredIfFailed":false,"type":"TEST_STEP","name":"setText","message":"Text \u0027fat\u0027 is set on object \u0027Object Repository/Signup_Customer/Last Name\u0027","description":"","startTime":1542294659899,"endTime":1542294660175,"childRecords":[{"testStatus":{"stackTrace":"","statusValue":"PASSED"},"type":"MESSAGE","name":"","message":"Text \u0027fat\u0027 is set on object \u0027Object Repository/Signup_Customer/Last Name\u0027","startTime":1542294660174,"endTime":0,"childRecords":[],"interuppted":false}],"interuppted":false},{"index":9,"isIgnoredIfFailed":false,"type":"TEST_STEP","name":"setText","message":"Text \u0027admin#123\u0027 is set on object \u0027Object Repository/Signup_Customer/Password\u0027","description":"","startTime":1542294660175,"endTime":1542294660457,"childRecords":[{"testStatus":{"stackTrace":"","statusValue":"PASSED"},"type":"MESSAGE","name":"","message":"Text \u0027admin#123\u0027 is set on object \u0027Object Repository/Signup_Customer/Password\u0027","startTime":1542294660455,"endTime":0,"childRecords":[],"interuppted":false}],"interuppted":false},{"index":10,"isIgnoredIfFailed":false,"type":"TEST_STEP","name":"setText","message":"Text \u002765464988465\u0027 is set on object \u0027Object Repository/Signup_Customer/Contact NO\u0027","description":"","startTime":1542294660457,"endTime":1542294660782,"childRecords":[{"testStatus":{"stackTrace":"","statusValue":"PASSED"},"type":"MESSAGE","name":"","message":"Text \u002765464988465\u0027 is set on object \u0027Object Repository/Signup_Customer/Contact NO\u0027","startTime":1542294660781,"endTime":0,"childRecords":[],"interuppted":false}],"interuppted":false},{"index":11,"isIgnoredIfFailed":false,"type":"TEST_STEP","name":"clickEvent.SelectServices.clickUsingJS1","message":"clickEvent.SelectServices.clickUsingJS1 is PASSED","description":"","startTime":1542294660782,"endTime":1542294660922,"childRecords":[{"testStatus":{"stackTrace":"","statusValue":"PASSED"},"type":"MESSAGE","name":"","message":"clickEvent.SelectServices.clickUsingJS1 is PASSED","startTime":1542294660921,"endTime":0,"childRecords":[],"interuppted":false}],"interuppted":false},{"index":12,"isIgnoredIfFailed":false,"type":"TEST_STEP","name":"Statement - Try","message":"Object: \u0027Object Repository/Signup_Customer/DuplicateEmail\u0027 is clicked on","description":"","startTime":1542294660923,"endTime":1542294662349,"childRecords":[{"index":1,"isIgnoredIfFailed":false,"type":"TEST_STEP","name":"verifyElementPresent","message":"Object \u0027Object Repository/Signup_Customer/DuplicateEmail\u0027 is present","description":"","startTime":1542294660924,"endTime":1542294662112,"childRecords":[{"testStatus":{"stackTrace":"","statusValue":"PASSED"},"type":"MESSAGE","name":"","message":"Object \u0027Object Repository/Signup_Customer/DuplicateEmail\u0027 is present","startTime":1542294662111,"endTime":0,"childRecords":[],"interuppted":false}],"interuppted":false},{"index":2,"isIgnoredIfFailed":false,"type":"TEST_STEP","name":"click","message":"Object: \u0027Object Repository/Signup_Customer/DuplicateEmail\u0027 is clicked on","description":"","startTime":1542294662112,"endTime":1542294662348,"childRecords":[{"testStatus":{"stackTrace":"","statusValue":"PASSED"},"type":"MESSAGE","name":"","message":"Object: \u0027Object Repository/Signup_Customer/DuplicateEmail\u0027 is clicked on","startTime":1542294662346,"endTime":0,"childRecords":[],"interuppted":false}],"interuppted":false}],"interuppted":false},{"index":15,"isIgnoredIfFailed":false,"type":"TEST_STEP","name":"closeBrowser","message":"Browser is closed","description":"","startTime":1542294662349,"endTime":1542294663141,"childRecords":[{"testStatus":{"stackTrace":"","statusValue":"PASSED"},"type":"MESSAGE","name":"","message":"Browser is closed","startTime":1542294663126,"endTime":0,"childRecords":[],"interuppted":false}],"interuppted":false}],"interuppted":false},{"testStatus":{"stackTrace":"","statusValue":"PASSED"},"type":"MESSAGE","name":"","message":"Test Cases/Sign-Up for Customer with Valid Inputs","startTime":1542294663142,"endTime":0,"childRecords":[],"interuppted":false}],"interuppted":false}],"interuppted":false}